burst_statsd/__init__.py
burst_statsd/constants.py
burst_statsd/stat_reader.py
burst_statsd/stat_reporter.py
burst_statsd-0.2.2.dist-info/LICENSE
burst_statsd-0.2.2.dist-info/METADATA
burst_statsd-0.2.2.dist-info/WHEEL
burst_statsd-0.2.2.dist-info/top_level.txt
burst_statsd-0.2.2.dist-info/RECORD
