Metadata-Version: 2.1
Name: burst-statsd
Version: 0.2.2
Summary: upload burst stat to statsd
Home-page: https://github.com/dantezhu/burst_statsd
Author: dantezhu
Author-email: dantezhu <zny2008@gmail.com>
License: MIT
Project-URL: Homepage, https://github.com/dantezhu/burst_statsd
Platform: any
License-File: LICENSE
Requires-Dist: statsd
